README.md
setup.py
bin/qualtrics
bin/qualtrics.cmd
examples/__init__.py
pyqualtrics/__init__.py
pyqualtrics/__main__.py
pyqualtrics/mock.py
pyqualtrics.egg-info/PKG-INFO
pyqualtrics.egg-info/SOURCES.txt
pyqualtrics.egg-info/dependency_links.txt
pyqualtrics.egg-info/requires.txt
pyqualtrics.egg-info/top_level.txt
tests/__init__.py
tests/pyqualtrics-ed.qsf
tests/pyqualtrics.qsf