Metadata-Version: 1.1
Name: pyqualtrics
Version: 0.6.7
Summary: Unofficial python SDK for Qualtrics API
Home-page: https://github.com/Baguage/pyqualtrics
Author: Alex Vyushkov
Author-email: pyqualtrics@gmail.com
License: Apache License 2.0
Keywords: API Qualtrics Survey SDK Social Science Psychology
Platform: UNKNOWN
Classifier: Development Status :: 4 - Beta
Classifier: License :: OSI Approved :: Apache Software License
Classifier: Intended Audience :: Developers
Classifier: Operating System :: OS Independent
Classifier: Programming Language :: Python
Classifier: Programming Language :: Python :: 2
Classifier: Programming Language :: Python :: 2.7
Classifier: Topic :: Software Development :: Libraries :: Python Modules
